loglady/__about__.py
loglady/__init__.py
loglady/__main__.py
loglady/_excepthook.py
loglady/_fallback.py
loglady/_tracebackhide.py
loglady/config.py
loglady/destination.py
loglady/logger.py
loglady/magics.py
loglady/manager.py
loglady/manager_stack.py
loglady/middleware.py
loglady/pytest.py
loglady/threading.py
loglady/transport.py
loglady/types.py
loglady/rich/__init__.py
loglady/rich/_stacktrace.py
loglady/rich/destination.py
loglady/rich/formatters.py
loglady-2025.2.7.dist-info/METADATA
loglady-2025.2.7.dist-info/WHEEL
loglady-2025.2.7.dist-info/entry_points.txt
loglady-2025.2.7.dist-info/licenses/LICENSE.txt
loglady-2025.2.7.dist-info/RECORD
