Metadata-Version: 2.4
Name: loglady
Version: 2025.2.7
Project-URL: Documentation, https://github.com/theacodes/loglady#readme
Project-URL: Issues, https://github.com/theacodes/loglady/issues
Project-URL: Source, https://github.com/theacodes/loglady
Author-email: Thea Flowers <me@thea.codes>
License-Expression: MIT
License-File: LICENSE.txt
Classifier: Development Status :: 4 - Beta
Classifier: Programming Language :: Python
Classifier: Programming Language :: Python :: 3.12
Classifier: Programming Language :: Python :: Implementation :: CPython
Requires-Python: >=3.12
Requires-Dist: rich
